{"cameraMode":{"drawMode":0,"name":"Shaded","section":"Shading Mode"},"sceneLighting":true,"audioPlay":false,"sceneViewState":{"showFog":true,"showMaterialUpdate":false,"showSkybox":true,"showFlares":true,"showImageEffects":true,"showParticleSystems":true},"in2DMode":false,"pivot":{"x":1.2139613628387452,"y":0.09968709945678711,"z":-279.51849365234377},"rotation":{"x":-0.4366506338119507,"y":0.19843734800815583,"z":-0.09938657283782959,"w":-0.8718263506889343},"size":6.122888088226318,"orthographic":false}